pure_sasl-0.5.1.dist-info/DESCRIPTION.rst
pure_sasl-0.5.1.dist-info/METADATA
pure_sasl-0.5.1.dist-info/RECORD
pure_sasl-0.5.1.dist-info/WHEEL
pure_sasl-0.5.1.dist-info/metadata.json
pure_sasl-0.5.1.dist-info/top_level.txt
puresasl/__init__.py
puresasl/client.py
puresasl/mechanisms.py
