Metadata-Version: 1.1
Name: pure-sasl
Version: 0.5.1
Summary: Pure Python client SASL implementation
Home-page: http://github.com/thobbs/pure-sasl
Author: Alex Shafer
Author-email: ashafer01@gmail.com
License: MIT
Keywords: sasl
Platform: UNKNOWN
Classifier: Development Status :: 4 - Beta
Classifier: Intended Audience :: Developers
Classifier: License :: OSI Approved :: MIT License
Classifier: Natural Language :: English
Classifier: Operating System :: OS Independent
Classifier: Programming Language :: Python :: 2.6
Classifier: Programming Language :: Python :: 2.7
Classifier: Programming Language :: Python :: 3.3
Classifier: Programming Language :: Python :: 3.4
Classifier: Programming Language :: Python :: 3.5
Classifier: Programming Language :: Python :: 3.6
Classifier: Topic :: Software Development :: Libraries :: Python Modules
